{"fields":[{"fieldname":"sb_op_settings","fieldtype":"Section Break","label":"Out Patient Settings"},{"fieldname":"patient_master_name","fieldtype":"Select","label":"Patient Name By","options":"Patient Name\nNaming Series"},{"fieldname":"manage_customer","fieldtype":"Check","label":"Manage Customer"},{"fieldname":"default_medical_code_standard","fieldtype":"Link","label":"Default Medical Code Standard","options":"Medical Code Standard"},{"fieldname":"column_break_9","fieldtype":"Column Break"},{"fieldname":"collect_registration_fee","fieldtype":"Check","label":"Collect Fee for Patient Registration"},{"fieldname":"registration_fee","fieldtype":"Currency","label":"Registration Fee","options":"Currency"},{"fieldname":"manage_appointment_invoice_automatically","fieldtype":"Check","label":"Invoice Appointments Automatically"},{"fieldname":"max_visit","fieldtype":"Int","label":"Patient Encounters in valid days"},{"fieldname":"valid_days","fieldtype":"Int","label":"Valid number of days"},{"fieldname":"healthcare_service_items","fieldtype":"Section Break","label":"Healthcare Service Items"},{"fieldname":"inpatient_visit_charge_item","fieldtype":"Link","label":"Inpatient Visit Charge Item","options":"Item"},{"fieldname":"op_consulting_charge_item","fieldtype":"Link","label":"Out Patient Consulting Charge Item","options":"Item"},{"fieldname":"column_break_13","fieldtype":"Column Break"},{"fieldname":"clinical_procedure_consumable_item","fieldtype":"Link","label":"Clinical Procedure Consumable Item","options":"Item"},{"fieldname":"out_patient_sms_alerts","fieldtype":"Section Break","label":"Out Patient SMS Alerts"},{"fieldname":"reg_sms","fieldtype":"Check","label":"Patient Registration"},{"fieldname":"reg_msg","fieldtype":"Small Text","label":"Registration Message"},{"fieldname":"app_con","fieldtype":"Check","label":"Appointment Confirmation"},{"fieldname":"app_con_msg","fieldtype":"Small Text","label":"Confirmation Message"},{"fieldname":"no_con","fieldtype":"Check","label":"Avoid Confirmation"},{"fieldname":"column_break_16","fieldtype":"Column Break"},{"fieldname":"app_rem","fieldtype":"Check","label":"Appointment Reminder"},{"fieldname":"app_rem_msg","fieldtype":"Small Text","label":"Reminder Message"},{"fieldname":"rem_before","fieldtype":"Time","label":"Remind Before"},{"fieldname":"sb_in_ac","fieldtype":"Section Break","label":"Income Account"},{"fieldname":"income_account","fieldtype":"Table","label":"Income Account","options":"Party Account"},{"fieldname":"sb_r_ac","fieldtype":"Section Break","label":"Receivable Account"},{"fieldname":"receivable_account","fieldtype":"Table","label":"Receivable Account","options":"Party Account"},{"fieldname":"sb_lab_settings","fieldtype":"Section Break","label":"Laboratory Settings"},{"fieldname":"create_test_on_si_submit","fieldtype":"Check","label":"Create Lab Test(s) on Sales Invoice Submit"},{"fieldname":"require_sample_collection","fieldtype":"Check","label":"Manage Sample Collection"},{"fieldname":"require_test_result_approval","fieldtype":"Check","label":"Require Lab Test Approval"},{"fieldname":"column_break_34","fieldtype":"Column Break"},{"fieldname":"employee_name_and_designation_in_print","fieldtype":"Check","label":"Employee name and designation in print"},{"fieldname":"custom_signature_in_print","fieldtype":"Small Text","label":"Custom Signature in Print"},{"fieldname":"laboratory_sms_alerts","fieldtype":"Section Break","label":"Laboratory SMS Alerts"},{"fieldname":"sms_printed","fieldtype":"Small Text","label":"Result Printed"},{"fieldname":"column_break_28","fieldtype":"Column Break"},{"fieldname":"sms_emailed","fieldtype":"Small Text","label":"Result Emailed"}]}