{"fields":[{"fieldname":"employee","fieldtype":"Link","label":"Employee","options":"Employee"},{"fieldname":"employee_name","fieldtype":"Data","label":"Employee Name","options":""},{"fieldname":"department","fieldtype":"Link","label":"Department","options":"Department"},{"fieldname":"company","fieldtype":"Link","label":"Company","options":"Company"},{"fieldname":"column_break_5","fieldtype":"Column Break"},{"fieldname":"from_date","fieldtype":"Date","label":"From Date"},{"fieldname":"to_date","fieldtype":"Date","label":"To Date"},{"fieldname":"half_day","fieldtype":"Check","label":"Half Day"},{"fieldname":"half_day_date","fieldtype":"Date","label":"Half Day Date"},{"fieldname":"reason_section","fieldtype":"Section Break","label":"Reason"},{"fieldname":"reason","fieldtype":"Select","label":"Reason","options":"Work From Home\nOn Duty"},{"fieldname":"column_break_4","fieldtype":"Column Break"},{"fieldname":"explanation","fieldtype":"Small Text","label":"Explanation"},{"fieldname":"amended_from","fieldtype":"Link","label":"Amended From","options":"Attendance Request"}]}