{"fields":[{"fieldname":"invoice_type","fieldtype":"Select","label":"Invoice Type","options":"Sales Invoice\nPurchase Invoice\nJournal Entry"},{"fieldname":"invoice_number","fieldtype":"Dynamic Link","label":"Invoice Number","options":"invoice_type"},{"fieldname":"invoice_date","fieldtype":"Date","label":"Invoice Date"},{"fieldname":"col_break1","fieldtype":"Column Break","label":""},{"fieldname":"amount","fieldtype":"Currency","label":"Amount"},{"fieldname":"outstanding_amount","fieldtype":"Currency","label":"Outstanding Amount"}]}