{"fields":[{"fieldname":"item_code","fieldtype":"Link","label":"Item Code","options":"Item"},{"fieldname":"serial_no","fieldtype":"Small Text","label":"Serial No"},{"fieldname":"qty","fieldtype":"Float","label":"Installed Qty"},{"fieldname":"description","fieldtype":"Text Editor","label":"Description"},{"fieldname":"prevdoc_detail_docname","fieldtype":"Data","label":"Against Document Detail No"},{"fieldname":"prevdoc_docname","fieldtype":"Data","label":"Against Document No"},{"fieldname":"prevdoc_doctype","fieldtype":"Data","label":"Document Type"}]}